solumdashboard/__init__.py
solumdashboard/dashboard.py
solumdashboard/exceptions.py
solumdashboard/version.py
solumdashboard/api/__init__.py
solumdashboard/api/client.py
solumdashboard/applications/__init__.py
solumdashboard/applications/forms.py
solumdashboard/applications/panel.py
solumdashboard/applications/tables.py
solumdashboard/applications/tabs.py
solumdashboard/applications/urls.py
solumdashboard/applications/views.py
solumdashboard/applications/workflows/__init__.py
solumdashboard/applications/workflows/update.py
solumdashboard/assemblies/__init__.py
solumdashboard/assemblies/panel.py
solumdashboard/assemblies/tables.py
solumdashboard/assemblies/tabs.py
solumdashboard/assemblies/urls.py
solumdashboard/assemblies/views.py
solumdashboard/common/workflow_parsers.py
solumdashboard/languagepacks/__init__.py
solumdashboard/languagepacks/forms.py
solumdashboard/languagepacks/panel.py
solumdashboard/languagepacks/tables.py
solumdashboard/languagepacks/urls.py
solumdashboard/languagepacks/views.py
solumdashboard/local/enabled/_50_solum.py
solumdashboard/locale/de/LC_MESSAGES/django.po
solumdashboard/locale/en_GB/LC_MESSAGES/django.po
solumdashboard/locale/id/LC_MESSAGES/django.po
solumdashboard/templates/applications/_create.html
solumdashboard/templates/applications/_detail.html
solumdashboard/templates/applications/_launch.html
solumdashboard/templates/applications/_log.html
solumdashboard/templates/applications/_scale.html
solumdashboard/templates/applications/create.html
solumdashboard/templates/applications/detail.html
solumdashboard/templates/applications/index.html
solumdashboard/templates/applications/launch.html
solumdashboard/templates/applications/scale.html
solumdashboard/templates/assemblies/_detail.html
solumdashboard/templates/assemblies/detail.html
solumdashboard/templates/assemblies/index.html
solumdashboard/templates/languagepacks/_create.html
solumdashboard/templates/languagepacks/_detail.html
solumdashboard/templates/languagepacks/create.html
solum_dashboard-11.0.0.dist-info/AUTHORS
solum_dashboard-11.0.0.dist-info/LICENSE
solum_dashboard-11.0.0.dist-info/METADATA
solum_dashboard-11.0.0.dist-info/WHEEL
solum_dashboard-11.0.0.dist-info/pbr.json
solum_dashboard-11.0.0.dist-info/top_level.txt
solum_dashboard-11.0.0.dist-info/RECORD
